compressive_transformer_pytorch/__init__.py
compressive_transformer_pytorch/autoregressive_wrapper.py
compressive_transformer_pytorch/compressive_transformer_pytorch.py
compressive_transformer_pytorch-0.4.0.dist-info/LICENSE
compressive_transformer_pytorch-0.4.0.dist-info/METADATA
compressive_transformer_pytorch-0.4.0.dist-info/WHEEL
compressive_transformer_pytorch-0.4.0.dist-info/top_level.txt
compressive_transformer_pytorch-0.4.0.dist-info/RECORD
