Metadata-Version: 2.1
Name: compressive-transformer-pytorch
Version: 0.4.0
Summary: Implementation of Compressive Transformer in Pytorch
Home-page: https://github.com/lucidrains/compressive-transformer-pytorch
Author: Phil Wang
Author-email: lucidrains@gmail.com
License: MIT
Keywords: attention,artificial intelligence,transformer,deep learning
Platform: UNKNOWN
Classifier: Development Status :: 4 - Beta
Classifier: Intended Audience :: Developers
Classifier: Topic :: Scientific/Engineering :: Artificial Intelligence
Classifier: License :: OSI Approved :: MIT License
Classifier: Programming Language :: Python :: 3.6
License-File: LICENSE
Requires-Dist: torch
Requires-Dist: mogrifier
